test_oct_25/__init__.py
test_oct_25-0.0.1.dist-info/LICENSE
test_oct_25-0.0.1.dist-info/WHEEL
test_oct_25-0.0.1.dist-info/METADATA
test_oct_25-0.0.1.dist-info/RECORD
