Metadata-Version: 2.1
Name: test_oct_25
Version: 0.0.1
Summary: this is a test package to show off flit
Home-page: https://github.com/Carreau/test_oct_25
License: UNKNOWN
Author: Matthias Bussonnier
Author-email: bussonniermatthias@gmail.com
Classifier: License :: OSI Approved :: MIT License
